kavk_api/__init__.py
kavk_api/api/base.py
kavk_api/api/methods.py
kavk_api/api/objects.py
kavk_api/api/responses.py
kavk_api/events/bot_events.py
kavk_api/events/enums.py
kavk_api/events/event_objects.py
kavk_api/events/user_events.py
kavk_api/exceptions.py
kavk_api/kavk_api.py
kavk_api/longpoll/__init__.py
kavk_api/longpoll/bot.py
kavk_api/longpoll/user.py
kavk_api/upload/__init__.py
kavk_api/upload/responses.py
kavk_api/upload/upload.py
kavk_api/utils.py
kavk_api-1.1.0.dist-info/LICENSE
kavk_api-1.1.0.dist-info/METADATA
kavk_api-1.1.0.dist-info/WHEEL
kavk_api-1.1.0.dist-info/RECORD
