Metadata-Version: 2.1
Name: kavk-api
Version: 1.1.0
Summary: 
License: MIT
Author: Kravandir
Author-email: kravandir@gmail.com
Requires-Python: >=3.10,<4.0
Classifier: License :: OSI Approved :: MIT License
Classifier: Programming Language :: Python :: 3
Classifier: Programming Language :: Python :: 3.10
Classifier: Programming Language :: Python :: 3.11
Requires-Dist: aiohttp (>=3.8.4,<4.0.0)
